nyt_article_search/__init__.py
nyt_article_search/sdk.py
nyt_article_search/hooks/__init__.py
nyt_article_search/hooks/hook.py
nyt_article_search/models/__init__.py
nyt_article_search/models/article.py
nyt_article_search/models/base.py
nyt_article_search/models/byline.py
nyt_article_search/models/facet.py
nyt_article_search/models/facet_fields.py
nyt_article_search/models/facet_filter.py
nyt_article_search/models/get_articlesearch_json_ok_response.py
nyt_article_search/models/headline.py
nyt_article_search/models/keyword.py
nyt_article_search/models/multimedia.py
nyt_article_search/models/person.py
nyt_article_search/models/sort.py
nyt_article_search/models/utils/cast_models.py
nyt_article_search/models/utils/json_map.py
nyt_article_search/net/__init__.py
nyt_article_search/net/environment/__init__.py
nyt_article_search/net/environment/environment.py
nyt_article_search/net/headers/__init__.py
nyt_article_search/net/headers/base_header.py
nyt_article_search/net/request_chain/__init__.py
nyt_article_search/net/request_chain/request_chain.py
nyt_article_search/net/request_chain/handlers/__init__.py
nyt_article_search/net/request_chain/handlers/base_handler.py
nyt_article_search/net/request_chain/handlers/hook_handler.py
nyt_article_search/net/request_chain/handlers/http_handler.py
nyt_article_search/net/request_chain/handlers/retry_handler.py
nyt_article_search/net/transport/__init__.py
nyt_article_search/net/transport/request.py
nyt_article_search/net/transport/request_error.py
nyt_article_search/net/transport/response.py
nyt_article_search/net/transport/serializer.py
nyt_article_search/net/transport/utils.py
nyt_article_search/services/__init__.py
nyt_article_search/services/search.py
nyt_article_search/services/utils/base_service.py
nyt_article_search/services/utils/default_headers.py
nyt_article_search/services/utils/validator.py
nyt_article_search-1.0.0.dist-info/LICENSE
nyt_article_search-1.0.0.dist-info/METADATA
nyt_article_search-1.0.0.dist-info/WHEEL
nyt_article_search-1.0.0.dist-info/top_level.txt
nyt_article_search-1.0.0.dist-info/RECORD
