Metadata-Version: 2.1
Name: nyt-article-search
Version: 1.0.0
Summary: Use the Article Search API to look up articles by keyword.
License: MIT
Requires-Python: >=3.7
License-File: LICENSE
Requires-Dist: requests >=2.31.0
